mindtrace/hardware/__init__.py
mindtrace/hardware/api/__init__.py
mindtrace/hardware/api/cameras/__init__.py
mindtrace/hardware/api/cameras/connection_manager.py
mindtrace/hardware/api/cameras/launcher.py
mindtrace/hardware/api/cameras/service.py
mindtrace/hardware/api/cameras/models/__init__.py
mindtrace/hardware/api/cameras/models/requests.py
mindtrace/hardware/api/cameras/models/responses.py
mindtrace/hardware/api/cameras/schemas/__init__.py
mindtrace/hardware/api/cameras/schemas/backend_schemas.py
mindtrace/hardware/api/cameras/schemas/capture_schemas.py
mindtrace/hardware/api/cameras/schemas/config_schemas.py
mindtrace/hardware/api/cameras/schemas/homography_schemas.py
mindtrace/hardware/api/cameras/schemas/info_schemas.py
mindtrace/hardware/api/cameras/schemas/lifecycle_schemas.py
mindtrace/hardware/api/cameras/schemas/network_schemas.py
mindtrace/hardware/api/cameras/schemas/stream_schemas.py
mindtrace/hardware/api/plcs/__init__.py
mindtrace/hardware/api/plcs/connection_manager.py
mindtrace/hardware/api/plcs/launcher.py
mindtrace/hardware/api/plcs/service.py
mindtrace/hardware/api/plcs/models/__init__.py
mindtrace/hardware/api/plcs/models/requests.py
mindtrace/hardware/api/plcs/models/responses.py
mindtrace/hardware/api/plcs/schemas/__init__.py
mindtrace/hardware/api/plcs/schemas/backend_schemas.py
mindtrace/hardware/api/plcs/schemas/lifecycle_schemas.py
mindtrace/hardware/api/plcs/schemas/status_schemas.py
mindtrace/hardware/api/plcs/schemas/tag_schemas.py
mindtrace/hardware/api/sensors/__init__.py
mindtrace/hardware/api/sensors/connection_manager.py
mindtrace/hardware/api/sensors/service.py
mindtrace/hardware/api/sensors/models/__init__.py
mindtrace/hardware/api/sensors/models/requests.py
mindtrace/hardware/api/sensors/models/responses.py
mindtrace/hardware/api/sensors/schemas/__init__.py
mindtrace/hardware/api/sensors/schemas/data.py
mindtrace/hardware/api/sensors/schemas/lifecycle.py
mindtrace/hardware/api/stereo_cameras/__init__.py
mindtrace_hardware-0.8.0.dist-info/licenses/LICENSE
mindtrace_hardware-0.8.0.dist-info/METADATA
mindtrace_hardware-0.8.0.dist-info/WHEEL
mindtrace_hardware-0.8.0.dist-info/entry_points.txt
mindtrace_hardware-0.8.0.dist-info/top_level.txt
mindtrace_hardware-0.8.0.dist-info/RECORD
