Metadata-Version: 2.4
Name: mindtrace-hardware
Version: 0.8.0
Summary: Hardware integration for Mindtrace
Author: Mindtrace Team
License-Expression: Apache-2.0
Project-URL: Homepage, https://mindtrace.ai
Project-URL: Repository, https://github.com/mindtrace/mindtrace/blob/main/mindtrace/hardware
Classifier: Programming Language :: Python :: 3
Classifier: Programming Language :: Python :: 3.12
License-File: LICENSE
Requires-Dist: mindtrace-core>=0.8.0
Requires-Dist: mindtrace-services>=0.8.0
Requires-Dist: mindtrace-storage>=0.8.0
Requires-Dist: opencv-python>=4.8.0
Requires-Dist: structlog>=23.0.0
Requires-Dist: python-dotenv>=1.0.0
Requires-Dist: numpy>=1.24.0
Requires-Dist: pycomm3>=1.2.14
Requires-Dist: python-snap7[cli]>=2.0.2
Requires-Dist: typer>=0.9.0
Requires-Dist: psutil>=5.9.0
Requires-Dist: rich>=13.0.0
Requires-Dist: pyyaml>=6.0.3
Requires-Dist: aiomqtt>=2.4.0
Provides-Extra: cameras-basler
Requires-Dist: pypylon>=3.0.0; extra == "cameras-basler"
Provides-Extra: cameras-genicam
Requires-Dist: harvesters>=1.4.0; extra == "cameras-genicam"
Requires-Dist: genicam>=1.5.0; extra == "cameras-genicam"
Provides-Extra: cameras-all
Requires-Dist: mindtrace-hardware[cameras-basler,cameras-genicam]>=0.8.0; extra == "cameras-all"
Provides-Extra: stereo-basler
Requires-Dist: pypylon>=3.0.0; extra == "stereo-basler"
Requires-Dist: plyfile>=1.0.0; extra == "stereo-basler"
Provides-Extra: stereo-all
Requires-Dist: mindtrace-hardware[stereo-basler]>=0.8.0; extra == "stereo-all"
Provides-Extra: hardware-all
Requires-Dist: mindtrace-hardware[cameras-all,stereo-all]>=0.8.0; extra == "hardware-all"
Provides-Extra: setup-tools
Requires-Dist: requests>=2.28.0; extra == "setup-tools"
Requires-Dist: tqdm>=4.64.0; extra == "setup-tools"
Provides-Extra: dev
Requires-Dist: pytest>=7.0; extra == "dev"
Requires-Dist: pytest-asyncio>=1.0.0; extra == "dev"
Requires-Dist: pytest-cov>=4.0; extra == "dev"
Requires-Dist: black>=23.0; extra == "dev"
Requires-Dist: ruff>=0.1.0; extra == "dev"
Dynamic: license-file
